decorateme/__init__.py
decorateme/_auto.py
decorateme/_behavior.py
decorateme/_doc.py
decorateme/_informative.py
decorateme/_over.py
decorateme/_status.py
decorateme/_utils.py
decorateme-0.3.0.dist-info/LICENSE.txt
decorateme-0.3.0.dist-info/WHEEL
decorateme-0.3.0.dist-info/METADATA
decorateme-0.3.0.dist-info/RECORD
