Metadata-Version: 2.1
Name: decorateme
Version: 0.3.0
Summary: Python decorators for str/repr, equality, immutability, and more.
Home-page: https://github.com/dmyersturnbull/decorate-me
License: Apache-2.0
Keywords: python,decorators,repr
Author: Douglas Myers-Turnbull
Maintainer: Douglas Myers-Turnbull
Requires-Python: >=3.8,<4.0
Classifier: Development Status :: 3 - Alpha
Classifier: Intended Audience :: Developers
Classifier: License :: OSI Approved :: Apache Software License
Classifier: Natural Language :: English
Classifier: Operating System :: OS Independent
Classifier: Programming Language :: Python :: 3
Classifier: Programming Language :: Python :: 3 :: Only
Classifier: Programming Language :: Python :: 3.10
Classifier: Programming Language :: Python :: 3.11
Classifier: Programming Language :: Python :: 3.8
Classifier: Programming Language :: Python :: 3.9
Classifier: Topic :: Software Development :: Libraries :: Python Modules
Project-URL: CI, https://github.com/dmyersturnbull/decorate-me/actions
Project-URL: Changelog, https://github.com/dmyersturnbull/decorate-me/blob/main/CHANGELOG.md
Project-URL: Documentation, https://decorate-me.readthedocs.io
Project-URL: Download, https://pypi.org/project/decorateme/
Project-URL: Issues, https://github.com/dmyersturnbull/decorate-me/issues
Project-URL: Repository, https://github.com/dmyersturnbull/decorate-me
